ipulse_shared_core_ftredge/__init__.py
ipulse_shared_core_ftredge/cache/__init__.py
ipulse_shared_core_ftredge/cache/shared_cache.py
ipulse_shared_core_ftredge/dependencies/__init__.py
ipulse_shared_core_ftredge/dependencies/auth_firebase_token_validation.py
ipulse_shared_core_ftredge/dependencies/auth_protected_router.py
ipulse_shared_core_ftredge/dependencies/authz_credit_extraction.py
ipulse_shared_core_ftredge/dependencies/authz_for_apis.py
ipulse_shared_core_ftredge/dependencies/firestore_client.py
ipulse_shared_core_ftredge/exceptions/__init__.py
ipulse_shared_core_ftredge/exceptions/base_exceptions.py
ipulse_shared_core_ftredge/exceptions/user_exceptions.py
ipulse_shared_core_ftredge/models/__init__.py
ipulse_shared_core_ftredge/models/base_api_response.py
ipulse_shared_core_ftredge/models/base_nosql_model.py
ipulse_shared_core_ftredge/models/credit_api_response.py
ipulse_shared_core_ftredge/models/custom_json_response.py
ipulse_shared_core_ftredge/models/time_series_packaged_dataset_model.py
ipulse_shared_core_ftredge/models/catalog/__init__.py
ipulse_shared_core_ftredge/models/catalog/subscriptionplan.py
ipulse_shared_core_ftredge/models/catalog/usertype.py
ipulse_shared_core_ftredge/models/user/__init__.py
ipulse_shared_core_ftredge/models/user/user_permissions.py
ipulse_shared_core_ftredge/models/user/user_subscription.py
ipulse_shared_core_ftredge/models/user/userauth.py
ipulse_shared_core_ftredge/models/user/userprofile.py
ipulse_shared_core_ftredge/models/user/userstatus.py
ipulse_shared_core_ftredge/monitoring/__init__.py
ipulse_shared_core_ftredge/monitoring/tracemon.py
ipulse_shared_core_ftredge/services/__init__.py
ipulse_shared_core_ftredge/services/charging_processors.py
ipulse_shared_core_ftredge/services/user_charging_service.py
ipulse_shared_core_ftredge/services/base/__init__.py
ipulse_shared_core_ftredge/services/base/base_firestore_service.py
ipulse_shared_core_ftredge/services/base/cache_aware_firestore_service.py
ipulse_shared_core_ftredge-27.9.1.dist-info/licenses/LICENCE
ipulse_shared_core_ftredge-27.9.1.dist-info/METADATA
ipulse_shared_core_ftredge-27.9.1.dist-info/WHEEL
ipulse_shared_core_ftredge-27.9.1.dist-info/top_level.txt
ipulse_shared_core_ftredge-27.9.1.dist-info/RECORD
