Metadata-Version: 2.4
Name: ipulse_shared_core_ftredge
Version: 27.9.1
Summary: Shared Core models and Logger util for the Pulse platform project. Using AI for financial advisory and investment management.
Home-page: https://github.com/TheFutureEdge/ipulse_shared_core
Author: Russlan Ramdowar
Classifier: Programming Language :: Python :: 3
Classifier: License :: OSI Approved :: MIT License
Classifier: Operating System :: OS Independent
Requires-Python: >=3.12
License-File: LICENCE
Requires-Dist: fastapi~=0.128.0
Requires-Dist: pydantic[email]~=2.12.5
Requires-Dist: python-dateutil~=2.9.0
Requires-Dist: ipulse_shared_base_ftredge~=12.12.0
Dynamic: author
Dynamic: classifier
Dynamic: home-page
Dynamic: license-file
Dynamic: requires-dist
Dynamic: requires-python
Dynamic: summary
